secread/__init__.py
secread/tests/__init__.py
secread/tests/data/get_secret_response.json
secread/tests/test_secread.py
secread/thycotic.py
secread-0.1.4.dist-info/LICENSE
secread-0.1.4.dist-info/WHEEL
secread-0.1.4.dist-info/METADATA
secread-0.1.4.dist-info/RECORD
